serial_util/__init__.py
serial_util/connect.py
serial_util/gui.py
serial_util/interface_core.py
serial_util/log_init.py
serial_util-0.1.0.dist-info/entry_points.txt
serial_util-0.1.0.dist-info/LICENSE
serial_util-0.1.0.dist-info/METADATA
serial_util-0.1.0.dist-info/WHEEL
serial_util-0.1.0.dist-info/RECORD
