Metadata-Version: 2.1
Name: serial_util
Version: 0.1.0
Summary: Utility functions for pySerial
License: AGPL-3.0
Author: Takuya Sasatani
Author-email: 33111879+t-sasatani@users.noreply.github.com
Requires-Python: >=3.11,<4.0
Classifier: License :: OSI Approved :: GNU Affero General Public License v3
Classifier: Programming Language :: Python :: 3
Classifier: Programming Language :: Python :: 3.11
Requires-Dist: coloredlogs (>=15.0.1,<16.0.0)
Requires-Dist: matplotlib (>=3.8.4,<4.0.0)
Requires-Dist: myst-parser (>=2.0.0,<3.0.0)
Requires-Dist: pyserial (>=3.5,<4.0)
Requires-Dist: sphinx (>=7.2.6,<8.0.0)
Requires-Dist: sphinx-rtd-theme (>=2.0.0,<3.0.0)
Requires-Dist: streamlit (>=1.33.0,<2.0.0)
